currencies_integrations/__init__.py
currencies_integrations/bitcoin.py
currencies_integrations/cli.py
currencies_integrations/connection.py
currencies_integrations/dolar.py
currencies_integrations/libra.py
currencies_integrations/utils.py
currencies_integrations-0.1.1.dist-info/LICENSE
currencies_integrations-0.1.1.dist-info/METADATA
currencies_integrations-0.1.1.dist-info/WHEEL
currencies_integrations-0.1.1.dist-info/entry_points.txt
currencies_integrations-0.1.1.dist-info/RECORD
