Metadata-Version: 2.1
Name: currencies-integrations
Version: 0.1.1
Summary: Projeto para facilitar na busca por cotações de recursos financeiros.
License: MIT
Author: Daniel Guzman
Author-email: dguzzz101@gmail.com
Requires-Python: >=3.11,<4.0
Classifier: Development Status :: 4 - Beta
Classifier: Environment :: Console
Classifier: License :: OSI Approved :: MIT License
Classifier: Natural Language :: Portuguese (Brazilian)
Classifier: Programming Language :: Python :: 3
Classifier: Programming Language :: Python :: 3.11
Classifier: Programming Language :: Python :: 3.12
Classifier: Topic :: Office/Business :: Financial
Requires-Dist: requests (>=2.31.0,<3.0.0)
Requires-Dist: rich (>=13.7.1,<14.0.0)
Requires-Dist: typer (>=0.12.3,<0.13.0)
Project-URL: Código, https://github.com/guzzz/currencies-integrations
Project-URL: Documentação, https://currencies-integrations.readthedocs.io/en/latest/
